Workbook
Name AFHomesStaff0: 'Reference Lists'!$A$2:$A$2
Name AFHomesStaff1: 'Reference Lists'!$B$2:$B$2
Name AFHomesStaff2: 'Reference Lists'!$C$2:$C$2
Name AFHomesStaff3: 'Reference Lists'!$D$2:$D$2
Name AFHomesEmpty: 'Address Lists'!$D$1
Name AFHomesProvinces: 'Address Lists'!$A$2:$A$84
Name AFHomesCities0: 'Address Lists'!$C$2:$AC$2
Name AFHomesCities1: 'Address Lists'!$C$3:$N$3
Name AFHomesCities2: 'Address Lists'!$C$4:$P$4
Name AFHomesCities3: 'Address Lists'!$C$5:$S$5
Name AFHomesCities4: 'Address Lists'!$C$6:$T$6
Name AFHomesCities5: 'Address Lists'!$C$7:$T$7
Name AFHomesCities6: 'Address Lists'!$C$8:$I$8
Name AFHomesCities7: 'Address Lists'!$C$9:$J$9
Name AFHomesCities8: 'Address Lists'!$C$10:$N$10
Name AFHomesCities9: 'Address Lists'!$C$11:$N$11
Name AFHomesCities10: 'Address Lists'!$C$12:$H$12
Name AFHomesCities11: 'Address Lists'!$C$13:$AJ$13
Name AFHomesCities12: 'Address Lists'!$C$14:$P$14
Name AFHomesCities13: 'Address Lists'!$C$15:$J$15
Name AFHomesCities14: 'Address Lists'!$C$16:$AX$16
Name AFHomesCities15: 'Address Lists'!$C$17:$X$17
Name AFHomesCities16: 'Address Lists'!$C$18:$Z$18
Name AFHomesCities17: 'Address Lists'!$C$19:$AE$19
Name AFHomesCities18: 'Address Lists'!$C$20:$N$20
Name AFHomesCities19: 'Address Lists'!$C$21:$AM$21
Name AFHomesCities20: 'Address Lists'!$C$22:$G$22
Name AFHomesCities21: 'Address Lists'!$C$23:$S$23
Name AFHomesCities22: 'Address Lists'!$C$24:$M$24
Name AFHomesCities23: 'Address Lists'!$C$25:$Y$25
Name AFHomesCities24: 'Address Lists'!$C$26:$BC$26
Name AFHomesCities25: 'Address Lists'!$C$27:$T$27
Name AFHomesCities26: 'Address Lists'!$C$28:$G$28
Name AFHomesCities27: 'Address Lists'!$C$29:$M$29
Name AFHomesCities28: 'Address Lists'!$C$30:$M$30
Name AFHomesCities29: 'Address Lists'!$C$31:$M$31
Name AFHomesCities30: 'Address Lists'!$C$32:$M$32
Name AFHomesCities31: 'Address Lists'!$C$33:$I$33
Name AFHomesCities32: 'Address Lists'!$C$34:$Y$34
Name AFHomesCities33: 'Address Lists'!$C$35:$G$35
Name AFHomesCities34: 'Address Lists'!$C$36:$M$36
Name AFHomesCities35: 'Address Lists'!$C$37:$Y$37
Name AFHomesCities36: 'Address Lists'!$C$38:$AJ$38
Name AFHomesCities37: 'Address Lists'!$C$39:$AT$39
Name AFHomesCities38: 'Address Lists'!$C$40:$AM$40
Name AFHomesCities39: 'Address Lists'!$C$41:$J$41
Name AFHomesCities40: 'Address Lists'!$C$42:$V$42
Name AFHomesCities41: 'Address Lists'!$C$43:$AF$43
Name AFHomesCities42: 'Address Lists'!$C$44:$Y$44
Name AFHomesCities43: 'Address Lists'!$C$45:$AP$45
Name AFHomesCities44: 'Address Lists'!$C$46:$AS$46
Name AFHomesCities45: 'Address Lists'!$C$47:$O$47
Name AFHomesCities46: 'Address Lists'!$C$48:$Z$48
Name AFHomesCities47: 'Address Lists'!$C$49:$H$49
Name AFHomesCities48: 'Address Lists'!$C$50:$W$50
Name AFHomesCities49: 'Address Lists'!$C$51:$S$51
Name AFHomesCities50: 'Address Lists'!$C$52:$S$52
Name AFHomesCities51: 'Address Lists'!$C$53:$AB$53
Name AFHomesCities52: 'Address Lists'!$C$54:$L$54
Name AFHomesCities53: 'Address Lists'!$C$55:$AH$55

Sheet Start Here
A1: AF Homes | Customer import
A2: Enter one purchase on Customers. On other tabs, select its VIP card ID / Purchase reference. No separate customer key.
A3: Customer ID (RA No.): copy the exact existing company Excel ID, even when that customer is not yet in this system.
A4: Only Gold can have an optional supplementary holder. Silver and Bronze cannot have supplementary holders.
A5: For genuinely new customers without a company ID, leave it blank to generate YYYY-NNNN (for example 2026-0001) on save.
A6: Reuse the same VIP card ID / Purchase reference when correcting or importing the same purchase again.
A7: Use one Birth date, Contract date or Payment date. Enter a date or use the calendar if your Excel supports it.
A8: Age calculates automatically. Citizenship is typed. Landline and TIN are optional; supplied TINs must be complete.
A9: Select Province, then City / Municipality, then Barangay. ZIP fills only from a unique postal reference match.
A10: Select the actual registered Referrer and VIP Recommender. They must share the same VD genealogy tree.
A11: List every actual payment once. Payment claim reference may be blank; the importer generates a stable reference.
A12: Separate identical payments need distinct claim references. Keep Receipt / Bank reference where available.
... A22: Points spending uses actual service or overnight dates in Philippine time, never the staff processing date. Allowances cannot exchange.

Sheet Customers
A1: Customer ID (RA No.) | B1: VIP card ID / Purchase reference (blank generates) | C1: Existing reservation reference | D1: Existing document status (optional) | E1: First name | F1: Last name | G1: Middle name | H1: Suffix | I1: Birth date | J1: Age (calculated) | K1: Gender | L1: Citizenship | M1: Civil status | N1: Address line 1 | O1: Address line 2 | P1: Province | Q1: City / Municipality | R1: Barangay | S1: Postal code | T1: Landline (optional) | U1: Email | V1: Mobile number | W1: TIN (optional) | X1: Occupation / Business name | Y1: Office / Business address | Z1: Position | AA1: VIP plan | AB1: Payment terms | AC1: Contract date | AD1: Regular contract price | AE1: Approved discount amount (claimed) | AF1: Contract total (calculated) | AG1: Included reservation fee | AH1: Payments stated (calculated) | AI1: Remaining balance (calculated) | AJ1: Existing card activation status | AK1: Existing Stay Points total | AL1: Existing card activation date | AM1: Existing card valid until | AN1: VIP purchase date (if known) | AO1: Payment term months for VIP ID (1-36; optional) | AP1: Contract type (new IDs: Standard)
D2: Pending | E2: Miguel | F2: Santos | G2: Reyes | I2: 1988-03-14 | J2: =IF(I2="","",DATEDIF(I2,TODAY(),"Y")) | K2: Male | L2: Filipino | M2: Married | N2: 18 Sampaguita Street | P2: Laguna | Q2: City of Calamba | R2: Bucal | S2: 4027 | U2: miguel.santos@afhomes-local.test | V2: 09178462510 | X2: Architect | AA2: BRONZE | AB2: Spot cash | AC2: 2026-10-01 | AD2: 60000.00 | AE2: 0.00 | AF2: =IF(B2="","",AD2-AE2) | AG2: 10000.00 | AH2: =IF(B2="","",SUMIF('Payments'!$A$2:$A$5001,B2,'Payments'!$D$2:$D$5001)) | AI2: =IF(B2="","",AF2-AH2) | AO2: 1 | AP2: Standard
A3: 2025-0782 | D3: Reservation Paid | E3: Isabella | F3: Mendoza | G3: Cruz | I3: 1992-07-22 | J3: =IF(I3="","",DATEDIF(I3,TODAY(),"Y")) | K3: Female | L3: Filipino | M3: Single | N3: 42 Mahogany Avenue | P3: Cavite | Q3: City of Tagaytay | R3: Kaybagal South | S3: 4120 | U3: isabella.mendoza@afhomes-local.test | V3: 09178462511 | X3: Pharmacist | AA3: BRONZE | AB3: Move a | AC3: 2026-10-01 | AD3: 60000.00 | AE3: 0.00 | AF3: =IF(B3="","",AD3-AE3) | AG3: 10000.00 | AH3: =IF(B3="","",SUMIF('Payments'!$A$2:$A$5001,B3,'Payments'!$D$2:$D$5001)) | AI3: =IF(B3="","",AF3-AH3) | AO3: 1 | AP3: Standard
D4: Partially Paid | E4: Rafael | F4: Bautista | G4: Navarro | I4: 1985-11-06 | J4: =IF(I4="","",DATEDIF(I4,TODAY(),"Y")) | K4: Male | L4: Filipino | M4: Married | N4: 7 Acacia Lane | P4: Batangas | Q4: City of Lipa | R4: Balintawak | S4: 4217 | U4: rafael.bautista@afhomes-local.test | V4: 09178462512 | X4: Civil Engineer | AA4: BRONZE | AB4: Installment 4_month | AC4: 2026-10-01 | AD4: 72000.00 | AE4: 0.00 | AF4: =IF(B4="","",AD4-AE4) | AG4: 10000.00 | AH4: =IF(B4="","",SUMIF('Payments'!$A$2:$A$5001,B4,'Payments'!$D$2:$D$5001)) | AI4: =IF(B4="","",AF4-AH4) | AO4: 4 | AP4: Standard
A5: 2025-0784 | D5: Down Payment | E5: Camille | F5: Villanueva | G5: Garcia | I5: 1990-02-18 | J5: =IF(I5="","",DATEDIF(I5,TODAY(),"Y")) | K5: Female | L5: Filipino | M5: Single | N5: 25 Ilang Ilang Street | P5: Rizal | Q5: City of Antipolo | R5: San Roque | S5: 1870 | U5: camille.villanueva@afhomes-local.test | V5: 09178462513 | X5: Accountant | AA5: SILVER | AB5: Move b1 40 12 | AC5: 2026-10-01 | AD5: 300000.00 | AE5: 0.00 | AF5: =IF(B5="","",AD5-AE5) | AG5: 10000.00 | AH5: =IF(B5="","",SUMIF('Payments'!$A$2:$A$5001,B5,'Payments'!$D$2:$D$5001)) | AI5: =IF(B5="","",AF5-AH5) | AO5: 12 | AP5: Standard
D6: Fully Paid | E6: Lorenzo | F6: Aquino | G6: Ramos | I6: 1983-09-10 | J6: =IF(I6="","",DATEDIF(I6,TODAY(),"Y")) | K6: Male | L6: Filipino | M6: Married | N6: 63 Narra Road | P6: Bulacan | Q6: City of Malolos | R6: Guinhawa | S6: 3000 | U6: lorenzo.aquino@afhomes-local.test | V6: 09178462514 | X6: Business Owner | AA6: GOLD | AB6: Move b2 25 12 | AC6: 2026-10-01 | AD6: 384000.00 | AE6: 0.00 | AF6: =IF(B6="","",AD6-AE6) | AG6: 10000.00 | AH6: =IF(B6="","",SUMIF('Payments'!$A$2:$A$5001,B6,'Payments'!$D$2:$D$5001)) | AI6: =IF(B6="","",AF6-AH6) | AO6: 12 | AP6: Standard
A7: 2025-0786 | B7: 26011500841G1C01S | D7: Active VIP | E7: Patricia | F7: Delos Reyes | G7: Flores | I7: 1989-05-27 | J7: =IF(I7="","",DATEDIF(I7,TODAY(),"Y")) | K7: Female | L7: Filipino | M7: Single | N7: 31 Rosal Street | P7: Pampanga | Q7: City of San Fernando | R7: Del Pilar | S7: 2000 | U7: patricia.delosreyes@afhomes-local.test | V7: 09178462515 | X7: Dentist | AA7: GOLD | AB7: Spot cash | AC7: 2026-01-15 | AD7: 312000.00 | AE7: 0.00 | AF7: =IF(B7="","",AD7-AE7) | AG7: 10000.00 | AH7: =IF(B7="","",SUMIF('Payments'!$A$2:$A$5001,B7,'Payments'!$D$2:$D$5001)) | AI7: =IF(B7="","",AF7-AH7) | AJ7: Active | AK7: 10000 | AL7: 2026-01-17 | AM7: 2031-01-17 | AO7: 1 | AP7: Standard
D8: Active VIP | E8: Gabriel | F8: Castillo | G8: Torres | I8: 1991-12-03 | J8: =IF(I8="","",DATEDIF(I8,TODAY(),"Y")) | K8: Male | L8: Filipino | M8: Married | N8: 9 Camia Drive | P8: Laguna | Q8: City of San Pablo | R8: San Rafael | S8: 4000 | U8: gabriel.castillo@afhomes-local.test | V8: 09178462516 | X8: IT Consultant | AA8: SILVER | AB8: Installment 4_month | AC8: 2026-01-15 | AD8: 300000.00 | AE8: 0.00 | AF8: =IF(B8="","",AD8-AE8) | AG8: 10000.00 | AH8: =IF(B8="","",SUMIF('Payments'!$A$2:$A$5001,B8,'Payments'!$D$2:$D$5001)) | AI8: =IF(B8="","",AF8-AH8) | AJ8: Active | AK8: 17500 | AL8: 2026-01-17 | AM8: 2031-01-17 | AO8: 4 | AP8: Standard
A9: 2025-0788 | B9: 25050100612S1T12N | D9: Expired | E9: Sofia | F9: Mercado | G9: Domingo | I9: 1986-08-15 | J9: =IF(I9="","",DATEDIF(I9,TODAY(),"Y")) | K9: Female | L9: Filipino | M9: Single | N9: 56 Molave Street | P9: Cavite | Q9: Silang | R9: Biga I | S9: 4118 | U9: sofia.mercado@afhomes-local.test | V9: 09178462517 | X9: Teacher | AA9: SILVER | AB9: Move b1 40 12 | AC9: 2025-05-01 | AD9: 300000.00 | AE9: 0.00 | AF9: =IF(B9="","",AD9-AE9) | AG9: 10000.00 | AH9: =IF(B9="","",SUMIF('Payments'!$A$2:$A$5001,B9,'Payments'!$D$2:$D$5001)) | AI9: =IF(B9="","",AF9-AH9) | AJ9: Expired | AK9: 4000 | AL9: 2025-05-03 | AM9: 2026-05-03 | AO9: 12 | AP9: Non-Standard
D10: Suspended | E10: Adrian | F10: Fernandez | G10: Gonzales | I10: 1980-04-29 | J10: =IF(I10="","",DATEDIF(I10,TODAY(),"Y")) | K10: Male | L10: Filipino | M10: Married | N10: 14 Yakal Avenue | P10: Batangas | Q10: City of Tanauan | R10: Darasa | S10: 4232 | U10: adrian.fernandez@afhomes-local.test | V10: 09178462518 | X10: Entrepreneur | AA10: BRONZE | AB10: Move a | AC10: 2026-01-15 | AD10: 60000.00 | AE10: 0.00 | AF10: =IF(B10="","",AD10-AE10) | AG10: 10000.00 | AH10: =IF(B10="","",SUMIF('Payments'!$A$2:$A$5001,B10,'Payments'!$D$2:$D$5001)) | AI10: =IF(B10="","",AF10-AH10) | AJ10: Suspended | AK10: 4000 | AL10: 2026-01-17 | AM10: 2031-01-17 | AO10: 1 | AP10: Standard
A11: 2025-0790 | D11: Cancelled | E11: Beatrice | F11: Salazar | G11: Dizon | I11: 1994-10-09 | J11: =IF(I11="","",DATEDIF(I11,TODAY(),"Y")) | K11: Female | L11: Filipino | M11: Single | N11: 88 Jasmine Street | P11: Bulacan | Q11: Santa Maria | R11: Poblacion | S11: 3022 | U11: beatrice.salazar@afhomes-local.test | V11: 09178462519 | X11: Physical Therapist | AA11: GOLD | AB11: Move b2 25 12 | AC11: 2026-01-15 | AD11: 384000.00 | AE11: 0.00 | AF11: =IF(B11="","",AD11-AE11) | AG11: 10000.00 | AH11: =IF(B11="","",SUMIF('Payments'!$A$2:$A$5001,B11,'Payments'!$D$2:$D$5001)) | AI11: =IF(B11="","",AF11-AH11) | AJ11: Cancelled | AK11: 4000 | AL11: 2026-01-17 | AM11: 2031-01-17 | AO11: 12 | AP11: Standard
J12: =IF(I12="","",DATEDIF(I12,TODAY(),"Y")) | S12: =IF(P12="","",IFERROR(VLOOKUP(P12&"|"&Q12&"|"&R12,'Postal Codes'!$A$2:$B$1516,2,FALSE),IFERROR(VLOOKUP(P12&"|"&Q12,'Postal Codes'!$A$2:$B$1516,2,FALSE),""))) | AF12: =IF(B12="","",AD12-AE12) | AH12: =IF(B12="","",SUMIF('Payments'!$A$2:$A$5001,B12,'Payments'!$D$2:$D$5001)) | AI12: =IF(B12="","",AF12-AH12)
J13: =IF(I13="","",DATEDIF(I13,TODAY(),"Y")) | S13: =IF(P13="","",IFERROR(VLOOKUP(P13&"|"&Q13&"|"&R13,'Postal Codes'!$A$2:$B$1516,2,FALSE),IFERROR(VLOOKUP(P13&"|"&Q13,'Postal Codes'!$A$2:$B$1516,2,FALSE),""))) | AF13: =IF(B13="","",AD13-AE13) | AH13: =IF(B13="","",SUMIF('Payments'!$A$2:$A$5001,B13,'Payments'!$D$2:$D$5001)) | AI13: =IF(B13="","",AF13-AH13)
J14: =IF(I14="","",DATEDIF(I14,TODAY(),"Y")) | S14: =IF(P14="","",IFERROR(VLOOKUP(P14&"|"&Q14&"|"&R14,'Postal Codes'!$A$2:$B$1516,2,FALSE),IFERROR(VLOOKUP(P14&"|"&Q14,'Postal Codes'!$A$2:$B$1516,2,FALSE),""))) | AF14: =IF(B14="","",AD14-AE14) | AH14: =IF(B14="","",SUMIF('Payments'!$A$2:$A$5001,B14,'Payments'!$D$2:$D$5001)) | AI14: =IF(B14="","",AF14-AH14)
J15: =IF(I15="","",DATEDIF(I15,TODAY(),"Y")) | S15: =IF(P15="","",IFERROR(VLOOKUP(P15&"|"&Q15&"|"&R15,'Postal Codes'!$A$2:$B$1516,2,FALSE),IFERROR(VLOOKUP(P15&"|"&Q15,'Postal Codes'!$A$2:$B$1516,2,FALSE),""))) | AF15: =IF(B15="","",AD15-AE15) | AH15: =IF(B15="","",SUMIF('Payments'!$A$2:$A$5001,B15,'Payments'!$D$2:$D$5001)) | AI15: =IF(B15="","",AF15-AH15)
J16: =IF(I16="","",DATEDIF(I16,TODAY(),"Y")) | S16: =IF(P16="","",IFERROR(VLOOKUP(P16&"|"&Q16&"|"&R16,'Postal Codes'!$A$2:$B$1516,2,FALSE),IFERROR(VLOOKUP(P16&"|"&Q16,'Postal Codes'!$A$2:$B$1516,2,FALSE),""))) | AF16: =IF(B16="","",AD16-AE16) | AH16: =IF(B16="","",SUMIF('Payments'!$A$2:$A$5001,B16,'Payments'!$D$2:$D$5001)) | AI16: =IF(B16="","",AF16-AH16)
J17: =IF(I17="","",DATEDIF(I17,TODAY(),"Y")) | S17: =IF(P17="","",IFERROR(VLOOKUP(P17&"|"&Q17&"|"&R17,'Postal Codes'!$A$2:$B$1516,2,FALSE),IFERROR(VLOOKUP(P17&"|"&Q17,'Postal Codes'!$A$2:$B$1516,2,FALSE),""))) | AF17: =IF(B17="","",AD17-AE17) | AH17: =IF(B17="","",SUMIF('Payments'!$A$2:$A$5001,B17,'Payments'!$D$2:$D$5001)) | AI17: =IF(B17="","",AF17-AH17)
J18: =IF(I18="","",DATEDIF(I18,TODAY(),"Y")) | S18: =IF(P18="","",IFERROR(VLOOKUP(P18&"|"&Q18&"|"&R18,'Postal Codes'!$A$2:$B$1516,2,FALSE),IFERROR(VLOOKUP(P18&"|"&Q18,'Postal Codes'!$A$2:$B$1516,2,FALSE),""))) | AF18: =IF(B18="","",AD18-AE18) | AH18: =IF(B18="","",SUMIF('Payments'!$A$2:$A$5001,B18,'Payments'!$D$2:$D$5001)) | AI18: =IF(B18="","",AF18-AH18)
J19: =IF(I19="","",DATEDIF(I19,TODAY(),"Y")) | S19: =IF(P19="","",IFERROR(VLOOKUP(P19&"|"&Q19&"|"&R19,'Postal Codes'!$A$2:$B$1516,2,FALSE),IFERROR(VLOOKUP(P19&"|"&Q19,'Postal Codes'!$A$2:$B$1516,2,FALSE),""))) | AF19: =IF(B19="","",AD19-AE19) | AH19: =IF(B19="","",SUMIF('Payments'!$A$2:$A$5001,B19,'Payments'!$D$2:$D$5001)) | AI19: =IF(B19="","",AF19-AH19)
J20: =IF(I20="","",DATEDIF(I20,TODAY(),"Y")) | S20: =IF(P20="","",IFERROR(VLOOKUP(P20&"|"&Q20&"|"&R20,'Postal Codes'!$A$2:$B$1516,2,FALSE),IFERROR(VLOOKUP(P20&"|"&Q20,'Postal Codes'!$A$2:$B$1516,2,FALSE),""))) | AF20: =IF(B20="","",AD20-AE20) | AH20: =IF(B20="","",SUMIF('Payments'!$A$2:$A$5001,B20,'Payments'!$D$2:$D$5001)) | AI20: =IF(B20="","",AF20-AH20)
J21: =IF(I21="","",DATEDIF(I21,TODAY(),"Y")) | S21: =IF(P21="","",IFERROR(VLOOKUP(P21&"|"&Q21&"|"&R21,'Postal Codes'!$A$2:$B$1516,2,FALSE),IFERROR(VLOOKUP(P21&"|"&Q21,'Postal Codes'!$A$2:$B$1516,2,FALSE),""))) | AF21: =IF(B21="","",AD21-AE21) | AH21: =IF(B21="","",SUMIF('Payments'!$A$2:$A$5001,B21,'Payments'!$D$2:$D$5001)) | AI21: =IF(B21="","",AF21-AH21)
J22: =IF(I22="","",DATEDIF(I22,TODAY(),"Y")) | S22: =IF(P22="","",IFERROR(VLOOKUP(P22&"|"&Q22&"|"&R22,'Postal Codes'!$A$2:$B$1516,2,FALSE),IFERROR(VLOOKUP(P22&"|"&Q22,'Postal Codes'!$A$2:$B$1516,2,FALSE),""))) | AF22: =IF(B22="","",AD22-AE22) | AH22: =IF(B22="","",SUMIF('Payments'!$A$2:$A$5001,B22,'Payments'!$D$2:$D$5001)) | AI22: =IF(B22="","",AF22-AH22)
J23: =IF(I23="","",DATEDIF(I23,TODAY(),"Y")) | S23: =IF(P23="","",IFERROR(VLOOKUP(P23&"|"&Q23&"|"&R23,'Postal Codes'!$A$2:$B$1516,2,FALSE),IFERROR(VLOOKUP(P23&"|"&Q23,'Postal Codes'!$A$2:$B$1516,2,FALSE),""))) | AF23: =IF(B23="","",AD23-AE23) | AH23: =IF(B23="","",SUMIF('Payments'!$A$2:$A$5001,B23,'Payments'!$D$2:$D$5001)) | AI23: =IF(B23="","",AF23-AH23)
... J101: =IF(I101="","",DATEDIF(I101,TODAY(),"Y")) | S101: =IF(P101="","",IFERROR(VLOOKUP(P101&"|"&Q101&"|"&R101,'Postal Codes'!$A$2:$B$1516,2,FALSE),IFERROR(VLOOKUP(P101&"|"&Q101,'Postal Codes'!$A$2:$B$1516,2,FALSE),""))) | AF101: =IF(B101="","",AD101-AE101) | AH101: =IF(B101="","",SUMIF('Payments'!$A$2:$A$5001,B101,'Payments'!$D$2:$D$5001)) | AI101: =IF(B101="","",AF101-AH101)

Sheet Supplementary Holders
A1: Gold purchase reference (select) | B1: First name | C1: Last name | D1: Middle name | E1: Suffix | F1: Birth date | G1: Age (calculated) | H1: Gender | I1: Citizenship | J1: Civil status | K1: Address line 1 | L1: Address line 2 | M1: Province | N1: City / Municipality | O1: Barangay | P1: Postal code | Q1: Landline (optional) | R1: Email | S1: Mobile number | T1: TIN (optional) | U1: Occupation / Business name | V1: Office / Business address | W1: Position
G2: =IF(F2="","",DATEDIF(F2,TODAY(),"Y")) | P2: =IF(M2="","",IFERROR(VLOOKUP(M2&"|"&N2&"|"&O2,'Postal Codes'!$A$2:$B$1516,2,FALSE),IFERROR(VLOOKUP(M2&"|"&N2,'Postal Codes'!$A$2:$B$1516,2,FALSE),"")))
G3: =IF(F3="","",DATEDIF(F3,TODAY(),"Y")) | P3: =IF(M3="","",IFERROR(VLOOKUP(M3&"|"&N3&"|"&O3,'Postal Codes'!$A$2:$B$1516,2,FALSE),IFERROR(VLOOKUP(M3&"|"&N3,'Postal Codes'!$A$2:$B$1516,2,FALSE),"")))
G4: =IF(F4="","",DATEDIF(F4,TODAY(),"Y")) | P4: =IF(M4="","",IFERROR(VLOOKUP(M4&"|"&N4&"|"&O4,'Postal Codes'!$A$2:$B$1516,2,FALSE),IFERROR(VLOOKUP(M4&"|"&N4,'Postal Codes'!$A$2:$B$1516,2,FALSE),"")))
G5: =IF(F5="","",DATEDIF(F5,TODAY(),"Y")) | P5: =IF(M5="","",IFERROR(VLOOKUP(M5&"|"&N5&"|"&O5,'Postal Codes'!$A$2:$B$1516,2,FALSE),IFERROR(VLOOKUP(M5&"|"&N5,'Postal Codes'!$A$2:$B$1516,2,FALSE),"")))
G6: =IF(F6="","",DATEDIF(F6,TODAY(),"Y")) | P6: =IF(M6="","",IFERROR(VLOOKUP(M6&"|"&N6&"|"&O6,'Postal Codes'!$A$2:$B$1516,2,FALSE),IFERROR(VLOOKUP(M6&"|"&N6,'Postal Codes'!$A$2:$B$1516,2,FALSE),"")))
G7: =IF(F7="","",DATEDIF(F7,TODAY(),"Y")) | P7: =IF(M7="","",IFERROR(VLOOKUP(M7&"|"&N7&"|"&O7,'Postal Codes'!$A$2:$B$1516,2,FALSE),IFERROR(VLOOKUP(M7&"|"&N7,'Postal Codes'!$A$2:$B$1516,2,FALSE),"")))
G8: =IF(F8="","",DATEDIF(F8,TODAY(),"Y")) | P8: =IF(M8="","",IFERROR(VLOOKUP(M8&"|"&N8&"|"&O8,'Postal Codes'!$A$2:$B$1516,2,FALSE),IFERROR(VLOOKUP(M8&"|"&N8,'Postal Codes'!$A$2:$B$1516,2,FALSE),"")))
G9: =IF(F9="","",DATEDIF(F9,TODAY(),"Y")) | P9: =IF(M9="","",IFERROR(VLOOKUP(M9&"|"&N9&"|"&O9,'Postal Codes'!$A$2:$B$1516,2,FALSE),IFERROR(VLOOKUP(M9&"|"&N9,'Postal Codes'!$A$2:$B$1516,2,FALSE),"")))
G10: =IF(F10="","",DATEDIF(F10,TODAY(),"Y")) | P10: =IF(M10="","",IFERROR(VLOOKUP(M10&"|"&N10&"|"&O10,'Postal Codes'!$A$2:$B$1516,2,FALSE),IFERROR(VLOOKUP(M10&"|"&N10,'Postal Codes'!$A$2:$B$1516,2,FALSE),"")))
G11: =IF(F11="","",DATEDIF(F11,TODAY(),"Y")) | P11: =IF(M11="","",IFERROR(VLOOKUP(M11&"|"&N11&"|"&O11,'Postal Codes'!$A$2:$B$1516,2,FALSE),IFERROR(VLOOKUP(M11&"|"&N11,'Postal Codes'!$A$2:$B$1516,2,FALSE),"")))
G12: =IF(F12="","",DATEDIF(F12,TODAY(),"Y")) | P12: =IF(M12="","",IFERROR(VLOOKUP(M12&"|"&N12&"|"&O12,'Postal Codes'!$A$2:$B$1516,2,FALSE),IFERROR(VLOOKUP(M12&"|"&N12,'Postal Codes'!$A$2:$B$1516,2,FALSE),"")))
G13: =IF(F13="","",DATEDIF(F13,TODAY(),"Y")) | P13: =IF(M13="","",IFERROR(VLOOKUP(M13&"|"&N13&"|"&O13,'Postal Codes'!$A$2:$B$1516,2,FALSE),IFERROR(VLOOKUP(M13&"|"&N13,'Postal Codes'!$A$2:$B$1516,2,FALSE),"")))
... G101: =IF(F101="","",DATEDIF(F101,TODAY(),"Y")) | P101: =IF(M101="","",IFERROR(VLOOKUP(M101&"|"&N101&"|"&O101,'Postal Codes'!$A$2:$B$1516,2,FALSE),IFERROR(VLOOKUP(M101&"|"&N101,'Postal Codes'!$A$2:$B$1516,2,FALSE),"")))

Sheet Sales Team
A1: Purchase reference (select customer) | B1: VD / SVD (workbook claim) | C1: SSM (workbook claim) | D1: SM (workbook claim) | E1: Referrer | F1: VIP Recommender | G1: Recommender contact | H1: Recommender email
A2: miguel.santos@afhomes-local.test | B2: Eduardo Manalo | C2: Cristina Vergara | D2: Roberto Alcantara | E2: Mariel Soriano | F2: Daniel Pineda | G2: =IFERROR(VLOOKUP(F2,'Reference Lists'!$F$2:$M$2,7,FALSE),"") | H2: =IFERROR(VLOOKUP(F2,'Reference Lists'!$F$2:$M$2,8,FALSE),"")
A3: 2025-0782 | B3: Eduardo Manalo | C3: Cristina Vergara | D3: Roberto Alcantara | E3: Mariel Soriano | F3: Daniel Pineda | G3: =IFERROR(VLOOKUP(F3,'Reference Lists'!$F$2:$M$2,7,FALSE),"") | H3: =IFERROR(VLOOKUP(F3,'Reference Lists'!$F$2:$M$2,8,FALSE),"")
A4: rafael.bautista@afhomes-local.test | B4: Eduardo Manalo | C4: Cristina Vergara | D4: Roberto Alcantara | E4: Mariel Soriano | F4: Daniel Pineda | G4: =IFERROR(VLOOKUP(F4,'Reference Lists'!$F$2:$M$2,7,FALSE),"") | H4: =IFERROR(VLOOKUP(F4,'Reference Lists'!$F$2:$M$2,8,FALSE),"")
A5: 2025-0784 | B5: Eduardo Manalo | C5: Cristina Vergara | D5: Roberto Alcantara | E5: Mariel Soriano | F5: Daniel Pineda | G5: =IFERROR(VLOOKUP(F5,'Reference Lists'!$F$2:$M$2,7,FALSE),"") | H5: =IFERROR(VLOOKUP(F5,'Reference Lists'!$F$2:$M$2,8,FALSE),"")
A6: lorenzo.aquino@afhomes-local.test | B6: Eduardo Manalo | C6: Cristina Vergara | D6: Roberto Alcantara | E6: Mariel Soriano | F6: Daniel Pineda | G6: =IFERROR(VLOOKUP(F6,'Reference Lists'!$F$2:$M$2,7,FALSE),"") | H6: =IFERROR(VLOOKUP(F6,'Reference Lists'!$F$2:$M$2,8,FALSE),"")
A7: 26011500841G1C01S | B7: Eduardo Manalo | C7: Cristina Vergara | D7: Roberto Alcantara | E7: Mariel Soriano | F7: Daniel Pineda | G7: =IFERROR(VLOOKUP(F7,'Reference Lists'!$F$2:$M$2,7,FALSE),"") | H7: =IFERROR(VLOOKUP(F7,'Reference Lists'!$F$2:$M$2,8,FALSE),"")
A8: gabriel.castillo@afhomes-local.test | B8: Eduardo Manalo | C8: Cristina Vergara | D8: Roberto Alcantara | E8: Mariel Soriano | F8: Daniel Pineda | G8: =IFERROR(VLOOKUP(F8,'Reference Lists'!$F$2:$M$2,7,FALSE),"") | H8: =IFERROR(VLOOKUP(F8,'Reference Lists'!$F$2:$M$2,8,FALSE),"")
A9: 25050100612S1T12N | B9: Eduardo Manalo | C9: Cristina Vergara | D9: Roberto Alcantara | E9: Mariel Soriano | F9: Daniel Pineda | G9: =IFERROR(VLOOKUP(F9,'Reference Lists'!$F$2:$M$2,7,FALSE),"") | H9: =IFERROR(VLOOKUP(F9,'Reference Lists'!$F$2:$M$2,8,FALSE),"")
A10: adrian.fernandez@afhomes-local.test | B10: Eduardo Manalo | C10: Cristina Vergara | D10: Roberto Alcantara | E10: Mariel Soriano | F10: Daniel Pineda | G10: =IFERROR(VLOOKUP(F10,'Reference Lists'!$F$2:$M$2,7,FALSE),"") | H10: =IFERROR(VLOOKUP(F10,'Reference Lists'!$F$2:$M$2,8,FALSE),"")
A11: 2025-0790 | B11: Eduardo Manalo | C11: Cristina Vergara | D11: Roberto Alcantara | E11: Mariel Soriano | F11: Daniel Pineda | G11: =IFERROR(VLOOKUP(F11,'Reference Lists'!$F$2:$M$2,7,FALSE),"") | H11: =IFERROR(VLOOKUP(F11,'Reference Lists'!$F$2:$M$2,8,FALSE),"")
G12: =IFERROR(VLOOKUP(F12,'Reference Lists'!$F$2:$M$2,7,FALSE),"") | H12: =IFERROR(VLOOKUP(F12,'Reference Lists'!$F$2:$M$2,8,FALSE),"")
G13: =IFERROR(VLOOKUP(F13,'Reference Lists'!$F$2:$M$2,7,FALSE),"") | H13: =IFERROR(VLOOKUP(F13,'Reference Lists'!$F$2:$M$2,8,FALSE),"")
G14: =IFERROR(VLOOKUP(F14,'Reference Lists'!$F$2:$M$2,7,FALSE),"") | H14: =IFERROR(VLOOKUP(F14,'Reference Lists'!$F$2:$M$2,8,FALSE),"")
G15: =IFERROR(VLOOKUP(F15,'Reference Lists'!$F$2:$M$2,7,FALSE),"") | H15: =IFERROR(VLOOKUP(F15,'Reference Lists'!$F$2:$M$2,8,FALSE),"")
G16: =IFERROR(VLOOKUP(F16,'Reference Lists'!$F$2:$M$2,7,FALSE),"") | H16: =IFERROR(VLOOKUP(F16,'Reference Lists'!$F$2:$M$2,8,FALSE),"")
G17: =IFERROR(VLOOKUP(F17,'Reference Lists'!$F$2:$M$2,7,FALSE),"") | H17: =IFERROR(VLOOKUP(F17,'Reference Lists'!$F$2:$M$2,8,FALSE),"")
G18: =IFERROR(VLOOKUP(F18,'Reference Lists'!$F$2:$M$2,7,FALSE),"") | H18: =IFERROR(VLOOKUP(F18,'Reference Lists'!$F$2:$M$2,8,FALSE),"")
G19: =IFERROR(VLOOKUP(F19,'Reference Lists'!$F$2:$M$2,7,FALSE),"") | H19: =IFERROR(VLOOKUP(F19,'Reference Lists'!$F$2:$M$2,8,FALSE),"")
G20: =IFERROR(VLOOKUP(F20,'Reference Lists'!$F$2:$M$2,7,FALSE),"") | H20: =IFERROR(VLOOKUP(F20,'Reference Lists'!$F$2:$M$2,8,FALSE),"")
G21: =IFERROR(VLOOKUP(F21,'Reference Lists'!$F$2:$M$2,7,FALSE),"") | H21: =IFERROR(VLOOKUP(F21,'Reference Lists'!$F$2:$M$2,8,FALSE),"")
G22: =IFERROR(VLOOKUP(F22,'Reference Lists'!$F$2:$M$2,7,FALSE),"") | H22: =IFERROR(VLOOKUP(F22,'Reference Lists'!$F$2:$M$2,8,FALSE),"")
G23: =IFERROR(VLOOKUP(F23,'Reference Lists'!$F$2:$M$2,7,FALSE),"") | H23: =IFERROR(VLOOKUP(F23,'Reference Lists'!$F$2:$M$2,8,FALSE),"")
... G101: =IFERROR(VLOOKUP(F101,'Reference Lists'!$F$2:$M$2,7,FALSE),"") | H101: =IFERROR(VLOOKUP(F101,'Reference Lists'!$F$2:$M$2,8,FALSE),"")

Sheet Payments
A1: Purchase reference (select customer) | B1: Payment claim reference (optional) | C1: Purpose | D1: Amount paid (claimed) | E1: Payment date | F1: Payment method | G1: Receipt / Bank reference | H1: Notes
A2: 2025-0782 | B2: RC-261002-1042 | C2: Reservation fee | D2: 10000.00 | E2: 2026-10-02 | F2: Bank transfer | G2: RC-261002-1042 | H2: Payment confirmed against archived receipt.
A3: rafael.bautista@afhomes-local.test | B3: RC-261002-1043 | C3: Down payment | D3: 30000.00 | E3: 2026-10-02 | F3: Cash | G3: RC-261002-1043 | H3: Payment confirmed against archived receipt.
A4: 2025-0784 | B4: RC-261002-1044 | C4: Down payment | D4: 120000.00 | E4: 2026-10-02 | F4: Bank transfer | G4: RC-261002-1044 | H4: Payment confirmed against archived receipt.
A5: lorenzo.aquino@afhomes-local.test | B5: RC-261002-1045 | C5: Full payment | D5: 384000.00 | E5: 2026-10-02 | F5: Cash | G5: RC-261002-1045 | H5: Payment confirmed against archived receipt.

Sheet Reference Lists
A1: VD / SVD | B1: SSM | C1: SM | D1: OST | F1: Registered staff | G1: Role | H1: AA number | I1: VD tree | J1: SSM | K1: SM | L1: Contact number | M1: Email | P1: Customer link: VIP ID / Customer ID / email
P2: =IF('Customers'!B2<>"",'Customers'!B2,IF('Customers'!A2<>"",'Customers'!A2,IF('Customers'!U2<>"",'Customers'!U2,"")))
P3: =IF('Customers'!B3<>"",'Customers'!B3,IF('Customers'!A3<>"",'Customers'!A3,IF('Customers'!U3<>"",'Customers'!U3,"")))
P4: =IF('Customers'!B4<>"",'Customers'!B4,IF('Customers'!A4<>"",'Customers'!A4,IF('Customers'!U4<>"",'Customers'!U4,"")))
P5: =IF('Customers'!B5<>"",'Customers'!B5,IF('Customers'!A5<>"",'Customers'!A5,IF('Customers'!U5<>"",'Customers'!U5,"")))
P6: =IF('Customers'!B6<>"",'Customers'!B6,IF('Customers'!A6<>"",'Customers'!A6,IF('Customers'!U6<>"",'Customers'!U6,"")))
P7: =IF('Customers'!B7<>"",'Customers'!B7,IF('Customers'!A7<>"",'Customers'!A7,IF('Customers'!U7<>"",'Customers'!U7,"")))
P8: =IF('Customers'!B8<>"",'Customers'!B8,IF('Customers'!A8<>"",'Customers'!A8,IF('Customers'!U8<>"",'Customers'!U8,"")))
P9: =IF('Customers'!B9<>"",'Customers'!B9,IF('Customers'!A9<>"",'Customers'!A9,IF('Customers'!U9<>"",'Customers'!U9,"")))
P10: =IF('Customers'!B10<>"",'Customers'!B10,IF('Customers'!A10<>"",'Customers'!A10,IF('Customers'!U10<>"",'Customers'!U10,"")))
P11: =IF('Customers'!B11<>"",'Customers'!B11,IF('Customers'!A11<>"",'Customers'!A11,IF('Customers'!U11<>"",'Customers'!U11,"")))
P12: =IF('Customers'!B12<>"",'Customers'!B12,IF('Customers'!A12<>"",'Customers'!A12,IF('Customers'!U12<>"",'Customers'!U12,"")))
P13: =IF('Customers'!B13<>"",'Customers'!B13,IF('Customers'!A13<>"",'Customers'!A13,IF('Customers'!U13<>"",'Customers'!U13,"")))
... P101: =IF('Customers'!B101<>"",'Customers'!B101,IF('Customers'!A101<>"",'Customers'!A101,IF('Customers'!U101<>"",'Customers'!U101,"")))

Sheet Address Lists
A1: Address group | B1: List reference | C1: Choices
A2: Abra | B2: AFHomesCities0 | C2: Bangued | D2: Boliney | E2: Bucay | F2: Bucloc | G2: Daguioman | H2: Danglas | I2: Dolores | J2: La Paz | K2: Lacub | L2: Lagangilang | M2: Lagayan | N2: Langiden | O2: Licuan-Baay | P2: Luba | Q2: Malibcong | R2: Manabo | S2: Peñarrubia | T2: Pidigan | U2: Pilar | V2: Sallapadan | W2: San Isidro | X2: San Juan | Y2: San Quintin | Z2: Tayum | AA2: Tineg | AB2: Tubo | AC2: Villaviciosa
A3: Agusan del Norte | B3: AFHomesCities1 | C3: Buenavista | D3: Carmen | E3: City of Butuan | F3: City of Cabadbaran | G3: Jabonga | H3: Kitcharao | I3: Las Nieves | J3: Magallanes | K3: Nasipit | L3: Remedios T. Romualdez | M3: Santiago | N3: Tubay
A4: Agusan del Sur | B4: AFHomesCities2 | C4: Bunawan | D4: City of Bayugan | E4: Esperanza | F4: La Paz | G4: Loreto | H4: Prosperidad | I4: Rosario | J4: San Francisco | K4: San Luis | L4: Santa Josefa | M4: Sibagat | N4: Talacogon | O4: Trento | P4: Veruela
A5: Aklan | B5: AFHomesCities3 | C5: Altavas | D5: Balete | E5: Banga | F5: Batan | G5: Buruanga | H5: Ibajay | I5: Kalibo | J5: Lezo | K5: Libacao | L5: Madalag | M5: Makato | N5: Malay | O5: Malinao | P5: Nabas | Q5: New Washington | R5: Numancia | S5: Tangalan
A6: Albay | B6: AFHomesCities4 | C6: Bacacay | D6: Camalig | E6: City of Legazpi | F6: City of Ligao | G6: City of Tabaco | H6: Daraga | I6: Guinobatan | J6: Jovellar | K6: Libon | L6: Malilipot | M6: Malinao | N6: Manito | O6: Oas | P6: Pio Duran | Q6: Polangui | R6: Rapu-Rapu | S6: Santo Domingo | T6: Tiwi
A7: Antique | B7: AFHomesCities5 | C7: Anini-Y | D7: Barbaza | E7: Belison | F7: Bugasong | G7: Caluya | H7: Culasi | I7: Hamtic | J7: Laua-An | K7: Libertad | L7: Pandan | M7: Patnongon | N7: San Jose | O7: San Remigio | P7: Sebaste | Q7: Sibalom | R7: Tibiao | S7: Tobias Fornier | T7: Valderrama
A8: Apayao | B8: AFHomesCities6 | C8: Calanasan | D8: Conner | E8: Flora | F8: Kabugao | G8: Luna | H8: Pudtol | I8: Santa Marcela
A9: Aurora | B9: AFHomesCities7 | C9: Baler | D9: Casiguran | E9: Dilasag | F9: Dinalungan | G9: Dingalan | H9: Dipaculao | I9: Maria Aurora | J9: San Luis
A10: Basilan | B10: AFHomesCities8 | C10: Akbar | D10: Al-Barka | E10: City of Lamitan | F10: Hadji Mohammad Ajul | G10: Hadji Muhtamad | H10: Lantawan | I10: Maluso | J10: Sumisip | K10: Tabuan-Lasa | L10: Tipo-Tipo | M10: Tuburan | N10: Ungkaya Pukan
A11: Bataan | B11: AFHomesCities9 | C11: Abucay | D11: Bagac | E11: City of Balanga | F11: Dinalupihan | G11: Hermosa | H11: Limay | I11: Mariveles | J11: Morong | K11: Orani | L11: Orion | M11: Pilar | N11: Samal
A12: Batanes | B12: AFHomesCities10 | C12: Basco | D12: Itbayat | E12: Ivana | F12: Mahatao | G12: Sabtang | H12: Uyugan
A13: Batangas | B13: AFHomesCities11 | C13: Agoncillo | D13: Alitagtag | E13: Balayan | F13: Balete | G13: Batangas City | H13: Bauan | I13: Calatagan | J13: City of Calaca | K13: City of Lipa | L13: City of Sto. Tomas | M13: City of Tanauan | N13: Cuenca | O13: Ibaan | P13: Laurel | Q13: Lemery | R13: Lian | S13: Lobo | T13: Mabini | U13: Malvar | V13: Mataasnakahoy | W13: Nasugbu | X13: Padre Garcia | Y13: Rosario | Z13: San Jose | AA13: San Juan | AB13: San Luis | AC13: San Nicolas | AD13: San Pascual | AE13: Santa Teresita | AF13: Taal | AG13: Talisay | AH13: Taysan | AI13: Tingloy | AJ13: Tuy
A14: Benguet | B14: AFHomesCities12 | C14: Atok | D14: Bakun | E14: Bokod | F14: Buguias | G14: City of Baguio | H14: Itogon | I14: Kabayan | J14: Kapangan | K14: Kibungan | L14: La Trinidad | M14: Mankayan | N14: Sablan | O14: Tuba | P14: Tublay
A15: Biliran | B15: AFHomesCities13 | C15: Almeria | D15: Biliran | E15: Cabucgayan | F15: Caibiran | G15: Culaba | H15: Kawayan | I15: Maripipi | J15: Naval
A16: Bohol | B16: AFHomesCities14 | C16: Alburquerque | D16: Alicia | E16: Anda | F16: Antequera | G16: Baclayon | H16: Balilihan | I16: Batuan | J16: Bien Unido | K16: Bilar | L16: Buenavista | M16: Calape | N16: Candijay | O16: Carmen | P16: Catigbian | Q16: City of Tagbilaran | R16: Clarin | S16: Corella | T16: Cortes | U16: Dagohoy | V16: Danao | W16: Dauis | X16: Dimiao | Y16: Duero | Z16: Garcia Hernandez | AA16: Getafe | AB16: Guindulman | AC16: Inabanga | AD16: Jagna | AE16: Lila | AF16: Loay | AG16: Loboc | AH16: Loon | AI16: Mabini | AJ16: Maribojoc | AK16: Panglao | AL16: Pilar | AM16: President Carlos P. Garcia | AN16: Sagbayan | AO16: San Isidro | AP16: San Miguel | AQ16: Sevilla | AR16: Sierra Bullones | AS16: Sikatuna | AT16: Talibon | AU16: Trinidad | AV16: Tubigon | AW16: Ubay | AX16: Valencia
A17: Bukidnon | B17: AFHomesCities15 | C17: Baungon | D17: Cabanglasan | E17: City of Malaybalay | F17: City of Valencia | G17: Damulog | H17: Dangcagan | I17: Don Carlos | J17: Impasug-ong | K17: Kadingilan | L17: Kalilangan | M17: Kibawe | N17: Kitaotao | O17: Lantapan | P17: Libona | Q17: Malitbog | R17: Manolo Fortich | S17: Maramag | T17: Pangantucan | U17: Quezon | V17: San Fernando | W17: Sumilao | X17: Talakag
A18: Bulacan | B18: AFHomesCities16 | C18: Angat | D18: Balagtas | E18: Bocaue | F18: Bulacan | G18: Bustos | H18: Calumpit | I18: City of Baliwag | J18: City of Malolos | K18: City of Meycauayan | L18: City of San Jose Del Monte | M18: Doña Remedios Trinidad | N18: Guiguinto | O18: Hagonoy | P18: Marilao | Q18: Norzagaray | R18: Obando | S18: Pandi | T18: Paombong | U18: Plaridel | V18: Pulilan | W18: San Ildefonso | X18: San Miguel | Y18: San Rafael | Z18: Santa Maria
A19: Cagayan | B19: AFHomesCities17 | C19: Abulug | D19: Alcala | E19: Allacapan | F19: Amulung | G19: Aparri | H19: Baggao | I19: Ballesteros | J19: Buguey | K19: Calayan | L19: Camalaniugan | M19: Claveria | N19: Enrile | O19: Gattaran | P19: Gonzaga | Q19: Iguig | R19: Lal-Lo | S19: Lasam | T19: Pamplona | U19: Peñablanca | V19: Piat | W19: Rizal | X19: Sanchez-Mira | Y19: Santa Ana | Z19: Santa Praxedes | AA19: Santa Teresita | AB19: Santo Niño | AC19: Solana | AD19: Tuao | AE19: Tuguegarao City
A20: Camarines Norte | B20: AFHomesCities18 | C20: Basud | D20: Capalonga | E20: Daet | F20: Jose Panganiban | G20: Labo | H20: Mercedes | I20: Paracale | J20: San Lorenzo Ruiz | K20: San Vicente | L20: Santa Elena | M20: Talisay | N20: Vinzons
A21: Camarines Sur | B21: AFHomesCities19 | C21: Baao | D21: Balatan | E21: Bato | F21: Bombon | G21: Buhi | H21: Bula | I21: Cabusao | J21: Calabanga | K21: Camaligan | L21: Canaman | M21: Caramoan | N21: City of Iriga | O21: City of Naga | P21: Del Gallego | Q21: Gainza | R21: Garchitorena | S21: Goa | T21: Lagonoy | U21: Libmanan | V21: Lupi | W21: Magarao | X21: Milaor | Y21: Minalabac | Z21: Nabua | AA21: Ocampo | AB21: Pamplona | AC21: Pasacao | AD21: Pili | AE21: Presentacion | AF21: Ragay | AG21: Sagñay | AH21: San Fernando | AI21: San Jose | AJ21: Sipocot | AK21: Siruma | AL21: Tigaon | AM21: Tinambac
A22: Camiguin | B22: AFHomesCities20 | C22: Catarman | D22: Guinsiliban | E22: Mahinog | F22: Mambajao | G22: Sagay
A23: Capiz | B23: AFHomesCities21 | C23: City of Roxas | D23: Cuartero | E23: Dao | F23: Dumalag | G23: Dumarao | H23: Ivisan | I23: Jamindan | J23: Ma-Ayon | K23: Mambusao | L23: Panay | M23: Panitan | N23: Pilar | O23: Pontevedra | P23: President Roxas | Q23: Sapi-An | R23: Sigma | S23: Tapaz
A24: Catanduanes | B24: AFHomesCities22 | C24: Bagamanoc | D24: Baras | E24: Bato | F24: Caramoran | G24: Gigmoto | H24: Pandan | I24: Panganiban | J24: San Andres | K24: San Miguel | L24: Viga | M24: Virac
A25: Cavite | B25: AFHomesCities23 | C25: Alfonso | D25: Amadeo | E25: Carmona | F25: City of Bacoor | G25: City of Cavite | H25: City of Dasmariñas | I25: City of General Trias | J25: City of Imus | K25: City of Tagaytay | L25: City of Trece Martires | M25: Gen. Mariano Alvarez | N25: General Emilio Aguinaldo | O25: Indang | P25: Kawit | Q25: Magallanes | R25: Maragondon | S25: Mendez | T25: Naic | U25: Noveleta | V25: Rosario | W25: Silang | X25: Tanza | Y25: Ternate
A26: Cebu | B26: AFHomesCities24 | C26: Alcantara | D26: Alcoy | E26: Alegria | F26: Aloguinsan | G26: Argao | H26: Asturias | I26: Badian | J26: Balamban | K26: Bantayan | L26: Barili | M26: Boljoon | N26: Borbon | O26: Carmen | P26: Catmon | Q26: City of Bogo | R26: City of Carcar | S26: City of Cebu | T26: City of Lapu-Lapu | U26: City of Mandaue | V26: City of Naga | W26: City of Talisay | X26: City of Toledo | Y26: Compostela | Z26: Consolacion | AA26: Cordova | AB26: Daanbantayan | AC26: Dalaguete | AD26: Danao City | AE26: Dumanjug | AF26: Ginatilan | AG26: Liloan | AH26: Madridejos | AI26: Malabuyoc | AJ26: Medellin | AK26: Minglanilla | AL26: Moalboal | AM26: Oslob | AN26: Pilar | AO26: Pinamungajan | AP26: Poro | AQ26: Ronda | AR26: Samboan | AS26: San Fernando | AT26: San Francisco | AU26: San Remigio | AV26: Santa Fe | AW26: Santander | AX26: Sibonga | AY26: Sogod | AZ26: Tabogon | BA26: Tabuelan | BB26: Tuburan | BC26: Tudela
A27: Cotabato | B27: AFHomesCities25 | C27: Alamada | D27: Aleosan | E27: Antipas | F27: Arakan | G27: Banisilan | H27: Carmen | I27: City of Kidapawan | J27: Kabacan | K27: Libungan | L27: M'Lang | M27: Magpet | N27: Makilala | O27: Matalam | P27: Midsayap | Q27: Pigkawayan | R27: Pikit | S27: President Roxas | T27: Tulunan
A28: Davao Occidental | B28: AFHomesCities26 | C28: Don Marcelino | D28: Jose Abad Santos | E28: Malita | F28: Santa Maria | G28: Sarangani
A29: Davao Oriental | B29: AFHomesCities27 | C29: Baganga | D29: Banaybanay | E29: Boston | F29: Caraga | G29: Cateel | H29: City of Mati | I29: Governor Generoso | J29: Lupon | K29: Manay | L29: San Isidro | M29: Tarragona
A30: Davao de Oro | B30: AFHomesCities28 | C30: Compostela | D30: Laak | E30: Mabini | F30: Maco | G30: Maragusan | H30: Mawab | I30: Monkayo | J30: Montevista | K30: Nabunturan | L30: New Bataan | M30: Pantukan
A31: Davao del Norte | B31: AFHomesCities29 | C31: Asuncion | D31: Braulio E. Dujali | E31: Carmen | F31: City of Panabo | G31: City of Tagum | H31: Island Garden City of Samal | I31: Kapalong | J31: New Corella | K31: San Isidro | L31: Santo Tomas | M31: Talaingod
A32: Davao del Sur | B32: AFHomesCities30 | C32: Bansalan | D32: City of Davao | E32: City of Digos | F32: Hagonoy | G32: Kiblawan | H32: Magsaysay | I32: Malalag | J32: Matanao | K32: Padada | L32: Santa Cruz | M32: Sulop
A33: Dinagat Islands | B33: AFHomesCities31 | C33: Basilisa | D33: Cagdianao | E33: Dinagat | F33: Libjo | G33: Loreto | H33: San Jose | I33: Tubajon
A34: Eastern Samar | B34: AFHomesCities32 | C34: Arteche | D34: Balangiga | E34: Balangkayan | F34: Can-Avid | G34: City of Borongan | H34: Dolores | I34: General Macarthur | J34: Giporlos | K34: Guiuan | L34: Hernani | M34: Jipapad | N34: Lawaan | O34: Llorente | P34: Maslog | Q34: Maydolong | R34: Mercedes | S34: Oras | T34: Quinapondan | U34: Salcedo | V34: San Julian | W34: San Policarpo | X34: Sulat | Y34: Taft
A35: Guimaras | B35: AFHomesCities33 | C35: Buenavista | D35: Jordan | E35: Nueva Valencia | F35: San Lorenzo | G35: Sibunag
A36: Ifugao | B36: AFHomesCities34 | C36: Aguinaldo | D36: Alfonso Lista | E36: Asipulo | F36: Banaue | G36: Hingyon | H36: Hungduan | I36: Kiangan | J36: Lagawe | K36: Lamut | L36: Mayoyao | M36: Tinoc
A37: Ilocos Norte | B37: AFHomesCities35 | C37: Adams | D37: Bacarra | E37: Badoc | F37: Bangui | G37: Banna | H37: Burgos | I37: Carasi | J37: City of Batac | K37: City of Laoag | L37: Currimao | M37: Dingras | N37: Dumalneg | O37: Marcos | P37: Nueva Era | Q37: Pagudpud | R37: Paoay | S37: Pasuquin | T37: Piddig | U37: Pinili | V37: San Nicolas | W37: Sarrat | X37: Solsona | Y37: Vintar
A38: Ilocos Sur | B38: AFHomesCities36 | C38: Alilem | D38: Banayoyo | E38: Bantay | F38: Burgos | G38: Cabugao | H38: Caoayan | I38: Cervantes | J38: City of Candon | K38: City of Vigan | L38: Galimuyod | M38: Gregorio del Pilar | N38: Lidlidda | O38: Magsingal | P38: Nagbukel | Q38: Narvacan | R38: Quirino | S38: Salcedo | T38: San Emilio | U38: San Esteban | V38: San Ildefonso | W38: San Juan | X38: San Vicente | Y38: Santa | Z38: Santa Catalina | AA38: Santa Cruz | AB38: Santa Lucia | AC38: Santa Maria | AD38: Santiago | AE38: Santo Domingo | AF38: Sigay | AG38: Sinait | AH38: Sugpon | AI38: Suyo | AJ38: Tagudin
A39: Iloilo | B39: AFHomesCities37 | C39: Ajuy | D39: Alimodian | E39: Anilao | F39: Badiangan | G39: Balasan | H39: Banate | I39: Barotac Nuevo | J39: Barotac Viejo | K39: Batad | L39: Bingawan | M39: Cabatuan | N39: Calinog | O39: Carles | P39: City of Iloilo | Q39: City of Passi | R39: Concepcion | S39: Dingle | T39: Dueñas | U39: Dumangas | V39: Estancia | W39: Guimbal | X39: Igbaras | Y39: Janiuay | Z39: Lambunao | AA39: Leganes | AB39: Lemery | AC39: Leon | AD39: Maasin | AE39: Miagao | AF39: Mina | AG39: New Lucena | AH39: Oton | AI39: Pavia | AJ39: Pototan | AK39: San Dionisio | AL39: San Enrique | AM39: San Joaquin | AN39: San Miguel | AO39: San Rafael | AP39: Santa Barbara | AQ39: Sara | AR39: Tigbauan | AS39: Tubungan | AT39: Zarraga
A40: Isabela | B40: AFHomesCities38 | C40: Alicia | D40: Angadanan | E40: Aurora | F40: Benito Soliven | G40: Burgos | H40: Cabagan | I40: Cabatuan | J40: City of Cauayan | K40: City of Ilagan | L40: City of Santiago | M40: Cordon | N40: Delfin Albano | O40: Dinapigue | P40: Divilacan | Q40: Echague | R40: Gamu | S40: Jones | T40: Luna | U40: Maconacon | V40: Mallig | W40: Naguilian | X40: Palanan | Y40: Quezon | Z40: Quirino | AA40: Ramon | AB40: Reina Mercedes | AC40: Roxas | AD40: San Agustin | AE40: San Guillermo | AF40: San Isidro | AG40: San Manuel | AH40: San Mariano | AI40: San Mateo | AJ40: San Pablo | AK40: Santa Maria | AL40: Santo Tomas | AM40: Tumauini
A41: Kalinga | B41: AFHomesCities39 | C41: Balbalan | D41: City of Tabuk | E41: Lubuagan | F41: Pasil | G41: Pinukpuk | H41: Rizal | I41: Tanudan | J41: Tinglayan
A42: La Union | B42: AFHomesCities40 | C42: Agoo | D42: Aringay | E42: Bacnotan | F42: Bagulin | G42: Balaoan | H42: Bangar | I42: Bauang | J42: Burgos | K42: Caba | L42: City of San Fernando | M42: Luna | N42: Naguilian | O42: Pugo | P42: Rosario | Q42: San Gabriel | R42: San Juan | S42: Santo Tomas | T42: Santol | U42: Sudipen | V42: Tubao
A43: Laguna | B43: AFHomesCities41 | C43: Alaminos | D43: Bay | E43: Calauan | F43: Cavinti | G43: City of Biñan | H43: City of Cabuyao | I43: City of Calamba | J43: City of San Pablo | K43: City of San Pedro | L43: City of Santa Rosa | M43: Famy | N43: Kalayaan | O43: Liliw | P43: Los Baños | Q43: Luisiana | R43: Lumban | S43: Mabitac | T43: Magdalena | U43: Majayjay | V43: Nagcarlan | W43: Paete | X43: Pagsanjan | Y43: Pakil | Z43: Pangil | AA43: Pila | AB43: Rizal | AC43: Santa Cruz | AD43: Santa Maria | AE43: Siniloan | AF43: Victoria
A44: Lanao del Norte | B44: AFHomesCities42 | C44: Bacolod | D44: Baloi | E44: Baroy | F44: City of Iligan | G44: Kapatagan | H44: Kauswagan | I44: Kolambugan | J44: Lala | K44: Linamon | L44: Magsaysay | M44: Maigo | N44: Matungao | O44: Munai | P44: Nunungan | Q44: Pantao Ragat | R44: Pantar | S44: Poona Piagapo | T44: Salvador | U44: Sapad | V44: Sultan Naga Dimaporo | W44: Tagoloan | X44: Tangcal | Y44: Tubod
A45: Lanao del Sur | B45: AFHomesCities43 | C45: Amai Manabilang | D45: Bacolod-Kalawi | E45: Balabagan | F45: Balindong | G45: Bayang | H45: Binidayan | I45: Buadiposo-Buntong | J45: Bubong | K45: Butig | L45: Calanogas | M45: City of Marawi | N45: Ditsaan-Ramain | O45: Ganassi | P45: Kapai | Q45: Kapatagan | R45: Lumba-Bayabao | S45: Lumbaca-Unayan | T45: Lumbatan | U45: Lumbayanague | V45: Madalum | W45: Madamba | X45: Maguing | Y45: Malabang | Z45: Marantao | AA45: Marogong | AB45: Masiu | AC45: Mulondo | AD45: Pagayawan | AE45: Piagapo | AF45: Picong | AG45: Poona Bayabao | AH45: Pualas | AI45: Saguiaran | AJ45: Sultan Dumalondong | AK45: Tagoloan Ii | AL45: Tamparan | AM45: Taraka | AN45: Tubaran | AO45: Tugaya | AP45: Wao
A46: Leyte | B46: AFHomesCities44 | C46: Abuyog | D46: Alangalang | E46: Albuera | F46: Babatngon | G46: Barugo | H46: Bato | I46: Burauen | J46: Calubian | K46: Capoocan | L46: Carigara | M46: City of Baybay | N46: City of Tacloban | O46: Dagami | P46: Dulag | Q46: Hilongos | R46: Hindang | S46: Inopacan | T46: Isabel | U46: Jaro | V46: Javier | W46: Julita | X46: Kananga | Y46: La Paz | Z46: Leyte | AA46: Macarthur | AB46: Mahaplag | AC46: Matag-Ob | AD46: Matalom | AE46: Mayorga | AF46: Merida | AG46: Ormoc City | AH46: Palo | AI46: Palompon | AJ46: Pastrana | AK46: San Isidro | AL46: San Miguel | AM46: Santa Fe | AN46: Tabango | AO46: Tabontabon | AP46: Tanauan | AQ46: Tolosa | AR46: Tunga | AS46: Villaba
A47: Maguindanao del Norte | B47: AFHomesCities45 | C47: Barira | D47: Buldon | E47: City of Cotabato | F47: Datu Blah T. Sinsuat | G47: Datu Odin Sinsuat | H47: Kabuntalan | I47: Matanog | J47: Northern Kabuntalan | K47: Parang | L47: Sultan Kudarat | M47: Sultan Mastura | N47: Talitay | O47: Upi
A48: Maguindanao del Sur | B48: AFHomesCities46 | C48: Ampatuan | D48: Buluan | E48: Datu Abdullah Sangki | F48: Datu Anggal Midtimbang | G48: Datu Hoffer Ampatuan | H48: Datu Paglas | I48: Datu Piang | J48: Datu Salibo | K48: Datu Saudi Ampatuan | L48: Datu Unsay | M48: Gen. S.K. Pendatun | N48: Guindulungan | O48: Mamasapano | P48: Mangudadatu | Q48: Pagagawan | R48: Pagalungan | S48: Paglat | T48: Pandag | U48: Rajah Buayan | V48: Shariff Aguak | W48: Shariff Saydona Mustapha | X48: South Upi | Y48: Sultan Sa Barongis | Z48: Talayan
A49: Marinduque | B49: AFHomesCities47 | C49: Boac | D49: Buenavista | E49: Gasan | F49: Mogpog | G49: Santa Cruz | H49: Torrijos
A50: Masbate | B50: AFHomesCities48 | C50: Aroroy | D50: Baleno | E50: Balud | F50: Batuan | G50: Cataingan | H50: Cawayan | I50: City of Masbate | J50: Claveria | K50: Dimasalang | L50: Esperanza | M50: Mandaon | N50: Milagros | O50: Mobo | P50: Monreal | Q50: Palanas | R50: Pio V. Corpus | S50: Placer | T50: San Fernando | U50: San Jacinto | V50: San Pascual | W50: Uson
A51: Metro Manila | B51: AFHomesCities49 | C51: City of Caloocan | D51: City of Las Piñas | E51: City of Makati | F51: City of Malabon | G51: City of Mandaluyong | H51: City of Manila | I51: City of Marikina | J51: City of Muntinlupa | K51: City of Navotas | L51: City of Parañaque | M51: City of Pasig | N51: City of San Juan | O51: City of Taguig | P51: City of Valenzuela | Q51: Pasay City | R51: Pateros | S51: Quezon City
A52: Misamis Occidental | B52: AFHomesCities50 | C52: Aloran | D52: Baliangao | E52: Bonifacio | F52: Calamba | G52: City of Oroquieta | H52: City of Ozamiz | I52: City of Tangub | J52: Clarin | K52: Concepcion | L52: Don Victoriano Chiongbian | M52: Jimenez | N52: Lopez Jaena | O52: Panaon | P52: Plaridel | Q52: Sapang Dalaga | R52: Sinacaban | S52: Tudela
A53: Misamis Oriental | B53: AFHomesCities51 | C53: Alubijid | D53: Balingasag | E53: Balingoan | F53: Binuangan | G53: City of Cagayan De Oro | H53: City of El Salvador | I53: City of Gingoog | J53: Claveria | K53: Gitagum | L53: Initao | M53: Jasaan | N53: Kinoguitan | O53: Lagonglong | P53: Laguindingan | Q53: Libertad | R53: Lugait | S53: Magsaysay | T53: Manticao | U53: Medina | V53: Naawan | W53: Opol | X53: Salay | Y53: Sugbongcogon | Z53: Tagoloan | AA53: Talisayan | AB53: Villanueva
A54: Mountain Province | B54: AFHomesCities52 | C54: Barlig | D54: Bauko | E54: Besao | F54: Bontoc | G54: Natonin | H54: Paracelis | I54: Sabangan | J54: Sadanga | K54: Sagada | L54: Tadian
A55: Negros Occidental | B55: AFHomesCities53 | C55: Binalbagan | D55: Calatrava | E55: Candoni | F55: Cauayan | G55: City of Bacolod | H55: City of Bago | I55: City of Cadiz | J55: City of Escalante | K55: City of Himamaylan | L55: City of Kabankalan | M55: City of La Carlota | N55: City of Sagay | O55: City of San Carlos | P55: City of Silay | Q55: City of Sipalay | R55: City of Talisay | S55: City of Victorias | T55: Enrique B. Magalona | U55: Hinigaran | V55: Hinoba-an | W55: Ilog | X55: Isabela | Y55: La Castellana | Z55: Manapla | AA55: Moises Padilla | AB55: Murcia | AC55: Pontevedra | AD55: Pulupandan | AE55: Salvador Benedicto | AF55: San Enrique | AG55: Toboso | AH55: Valladolid
A56: Negros Oriental | B56: AFHomesCities54 | C56: Amlan | D56: Ayungon | E56: Bacong | F56: Basay | G56: Bindoy | H56: City of Bais | I56: City of Bayawan | J56: City of Canlaon | K56: City of Dumaguete | L56: City of Guihulngan | M56: City of Tanjay | N56: Dauin | O56: Jimalalud | P56: La Libertad | Q56: Mabinay | R56: Manjuyod | S56: Pamplona | T56: San Jose | U56: Santa Catalina | V56: Siaton | W56: Sibulan | X56: Tayasan | Y56: Valencia | Z56: Vallehermoso | AA56: Zamboanguita
A57: Northern Samar | B57: AFHomesCities55 | C57: Allen | D57: Biri | E57: Bobon | F57: Capul | G57: Catarman | H57: Catubig | I57: Gamay | J57: Laoang | K57: Lapinig | L57: Las Navas | M57: Lavezares | N57: Lope De Vega | O57: Mapanas | P57: Mondragon | Q57: Palapag | R57: Pambujan | S57: Rosario | T57: San Antonio | U57: San Isidro | V57: San Jose | W57: San Roque | X57: San Vicente | Y57: Silvino Lobos | Z57: Victoria
A58: Nueva Ecija | B58: AFHomesCities56 | C58: Aliaga | D58: Bongabon | E58: Cabiao | F58: Carranglan | G58: City of Cabanatuan | H58: City of Gapan | I58: City of Palayan | J58: Cuyapo | K58: Gabaldon | L58: General Mamerto Natividad | M58: General Tinio | N58: Guimba | O58: Jaen | P58: Laur | Q58: Licab | R58: Llanera | S58: Lupao | T58: Nampicuan | U58: Pantabangan | V58: Peñaranda | W58: Quezon | X58: Rizal | Y58: San Antonio | Z58: San Isidro | AA58: San Jose City | AB58: San Leonardo | AC58: Santa Rosa | AD58: Santo Domingo | AE58: Science City of Muñoz | AF58: Talavera | AG58: Talugtug | AH58: Zaragoza
A59: Nueva Vizcaya | B59: AFHomesCities57 | C59: Alfonso Castaneda | D59: Ambaguio | E59: Aritao | F59: Bagabag | G59: Bambang | H59: Bayombong | I59: Diadi | J59: Dupax del Norte | K59: Dupax del Sur | L59: Kasibu | M59: Kayapa | N59: Quezon | O59: Santa Fe | P59: Solano | Q59: Villaverde
A60: Occidental Mindoro | B60: AFHomesCities58 | C60: Abra De Ilog | D60: Calintaan | E60: Looc | F60: Lubang | G60: Magsaysay | H60: Mamburao | I60: Paluan | J60: Rizal | K60: Sablayan | L60: San Jose | M60: Santa Cruz
A61: Oriental Mindoro | B61: AFHomesCities59 | C61: Baco | D61: Bansud | E61: Bongabong | F61: Bulalacao | G61: City of Calapan | H61: Gloria | I61: Mansalay | J61: Naujan | K61: Pinamalayan | L61: Pola | M61: Puerto Galera | N61: Roxas | O61: San Teodoro | P61: Socorro | Q61: Victoria
A62: Palawan | B62: AFHomesCities60 | C62: Aborlan | D62: Agutaya | E62: Araceli | F62: Balabac | G62: Bataraza | H62: Brooke'S Point | I62: Busuanga | J62: Cagayancillo | K62: City of Puerto Princesa | L62: Coron | M62: Culion | N62: Cuyo | O62: Dumaran | P62: El Nido | Q62: Kalayaan | R62: Linapacan | S62: Magsaysay | T62: Narra | U62: Quezon | V62: Rizal | W62: Roxas | X62: San Vicente | Y62: Sofronio Española | Z62: Taytay
A63: Pampanga | B63: AFHomesCities61 | C63: Apalit | D63: Arayat | E63: Bacolor | F63: Candaba | G63: City of Angeles | H63: City of San Fernando | I63: Floridablanca | J63: Guagua | K63: Lubao | L63: Mabalacat City | M63: Macabebe | N63: Magalang | O63: Masantol | P63: Mexico | Q63: Minalin | R63: Porac | S63: San Luis | T63: San Simon | U63: Santa Ana | V63: Santa Rita | W63: Sasmuan | X63: Sto. Tomas
A64: Pangasinan | B64: AFHomesCities62 | C64: Agno | D64: Aguilar | E64: Alcala | F64: Anda | G64: Asingan | H64: Balungao | I64: Bani | J64: Basista | K64: Bautista | L64: Bayambang | M64: Binalonan | N64: Binmaley | O64: Bolinao | P64: Bugallon | Q64: Burgos | R64: Calasiao | S64: City of Alaminos | T64: City of Dagupan | U64: City of San Carlos | V64: City of Urdaneta | W64: Dasol | X64: Infanta | Y64: Labrador | Z64: Laoac | AA64: Lingayen | AB64: Mabini | AC64: Malasiqui | AD64: Manaoag | AE64: Mangaldan | AF64: Mangatarem | AG64: Mapandan | AH64: Natividad | AI64: Pozorrubio | AJ64: Rosales | AK64: San Fabian | AL64: San Jacinto | AM64: San Manuel | AN64: San Nicolas | AO64: San Quintin | AP64: Santa Barbara | AQ64: Santa Maria | AR64: Santo Tomas | AS64: Sison | AT64: Sual | AU64: Tayug | AV64: Umingan | AW64: Urbiztondo | AX64: Villasis
A65: Quezon | B65: AFHomesCities63 | C65: Agdangan | D65: Alabat | E65: Atimonan | F65: Buenavista | G65: Burdeos | H65: Calauag | I65: Candelaria | J65: Catanauan | K65: City of Lucena | L65: City of Tayabas | M65: Dolores | N65: General Luna | O65: General Nakar | P65: Guinayangan | Q65: Gumaca | R65: Infanta | S65: Jomalig | T65: Lopez | U65: Lucban | V65: Macalelon | W65: Mauban | X65: Mulanay | Y65: Padre Burgos | Z65: Pagbilao | AA65: Panukulan | AB65: Patnanungan | AC65: Perez | AD65: Pitogo | AE65: Plaridel | AF65: Polillo | AG65: Quezon | AH65: Real | AI65: Sampaloc | AJ65: San Andres | AK65: San Antonio | AL65: San Francisco | AM65: San Narciso | AN65: Sariaya | AO65: Tagkawayan | AP65: Tiaong | AQ65: Unisan
A66: Quirino | B66: AFHomesCities64 | C66: Aglipay | D66: Cabarroguis | E66: Diffun | F66: Maddela | G66: Nagtipunan | H66: Saguday
A67: Rizal | B67: AFHomesCities65 | C67: Angono | D67: Baras | E67: Binangonan | F67: Cainta | G67: Cardona | H67: City of Antipolo | I67: Jala-Jala | J67: Morong | K67: Pililla | L67: Rodriguez | M67: San Mateo | N67: Tanay | O67: Taytay | P67: Teresa
A68: Romblon | B68: AFHomesCities66 | C68: Alcantara | D68: Banton | E68: Cajidiocan | F68: Calatrava | G68: Concepcion | H68: Corcuera | I68: Ferrol | J68: Looc | K68: Magdiwang | L68: Odiongan | M68: Romblon | N68: San Agustin | O68: San Andres | P68: San Fernando | Q68: San Jose | R68: Santa Fe | S68: Santa Maria
A69: Samar | B69: AFHomesCities67 | C69: Almagro | D69: Basey | E69: Calbiga | F69: City of Calbayog | G69: City of Catbalogan | H69: Daram | I69: Gandara | J69: Hinabangan | K69: Jiabong | L69: Marabut | M69: Matuguinao | N69: Motiong | O69: Pagsanghan | P69: Paranas | Q69: Pinabacdao | R69: San Jorge | S69: San Jose De Buan | T69: San Sebastian | U69: Santa Margarita | V69: Santa Rita | W69: Santo Niño | X69: Tagapul-An | Y69: Talalora | Z69: Tarangnan | AA69: Villareal | AB69: Zumarraga
A70: Sarangani | B70: AFHomesCities68 | C70: Alabel | D70: Glan | E70: Kiamba | F70: Maasim | G70: Maitum | H70: Malapatan | I70: Malungon
A71: Siquijor | B71: AFHomesCities69 | C71: Enrique Villanueva | D71: Larena | E71: Lazi | F71: Maria | G71: San Juan | H71: Siquijor
A72: Sorsogon | B72: AFHomesCities70 | C72: Barcelona | D72: Bulan | E72: Bulusan | F72: Casiguran | G72: Castilla | H72: City of Sorsogon | I72: Donsol | J72: Gubat | K72: Irosin | L72: Juban | M72: Magallanes | N72: Matnog | O72: Pilar | P72: Prieto Diaz | Q72: Santa Magdalena
A73: South Cotabato | B73: AFHomesCities71 | C73: Banga | D73: City of General Santos | E73: City of Koronadal | F73: Lake Sebu | G73: Norala | H73: Polomolok | I73: Santo Niño | J73: Surallah | K73: T'Boli | L73: Tampakan | M73: Tantangan | N73: Tupi
A74: Southern Leyte | B74: AFHomesCities72 | C74: Anahawan | D74: Bontoc | E74: City of Maasin | F74: Hinunangan | G74: Hinundayan | H74: Libagon | I74: Liloan | J74: Limasawa | K74: Macrohon | L74: Malitbog | M74: Padre Burgos | N74: Pintuyan | O74: Saint Bernard | P74: San Francisco | Q74: San Juan | R74: San Ricardo | S74: Silago | T74: Sogod | U74: Tomas Oppus
A75: Sultan Kudarat | B75: AFHomesCities73 | C75: Bagumbayan | D75: City of Tacurong | E75: Columbio | F75: Esperanza | G75: Isulan | H75: Kalamansig | I75: Lambayong | J75: Lebak | K75: Lutayan | L75: Palimbang | M75: President Quirino | N75: Sen. Ninoy Aquino
A76: Sulu | B76: AFHomesCities74 | C76: Hadji Panglima Tahil | D76: Indanan | E76: Jolo | F76: Kalingalan Caluang | G76: Lugus | H76: Luuk | I76: Maimbung | J76: Old Panamao | K76: Omar | L76: Pandami | M76: Panglima Estino | N76: Pangutaran | O76: Parang | P76: Pata | Q76: Patikul | R76: Siasi | S76: Talipao | T76: Tapul | U76: Tongkil
A77: Surigao del Norte | B77: AFHomesCities75 | C77: Alegria | D77: Bacuag | E77: Burgos | F77: City of Surigao | G77: Claver | H77: Dapa | I77: Del Carmen | J77: General Luna | K77: Gigaquit | L77: Mainit | M77: Malimono | N77: Pilar | O77: Placer | P77: San Benito | Q77: San Francisco | R77: San Isidro | S77: Santa Monica | T77: Sison | U77: Socorro | V77: Tagana-An | W77: Tubod
A78: Surigao del Sur | B78: AFHomesCities76 | C78: Barobo | D78: Bayabas | E78: Cagwait | F78: Cantilan | G78: Carmen | H78: Carrascal | I78: City of Bislig | J78: City of Tandag | K78: Cortes | L78: Hinatuan | M78: Lanuza | N78: Lianga | O78: Lingig | P78: Madrid | Q78: Marihatag | R78: San Agustin | S78: San Miguel | T78: Tagbina | U78: Tago
A79: Tarlac | B79: AFHomesCities77 | C79: Anao | D79: Bamban | E79: Camiling | F79: Capas | G79: City of Tarlac | H79: Concepcion | I79: Gerona | J79: La Paz | K79: Mayantoc | L79: Moncada | M79: Paniqui | N79: Pura | O79: Ramos | P79: San Clemente | Q79: San Jose | R79: San Manuel | S79: Santa Ignacia | T79: Victoria
A80: Tawi-Tawi | B80: AFHomesCities78 | C80: Bongao | D80: Languyan | E80: Mapun | F80: Panglima Sugala | G80: Sapa-Sapa | H80: Sibutu | I80: Simunul | J80: Sitangkai | K80: South Ubian | L80: Tandubas | M80: Turtle Islands
A81: Zambales | B81: AFHomesCities79 | C81: Botolan | D81: Cabangan | E81: Candelaria | F81: Castillejos | G81: City of Olongapo | H81: Iba | I81: Masinloc | J81: Palauig | K81: San Antonio | L81: San Felipe | M81: San Marcelino | N81: San Narciso | O81: Santa Cruz | P81: Subic
A82: Zamboanga Sibugay | B82: AFHomesCities80 | C82: Alicia | D82: Buug | E82: City of Isabela | F82: Diplahan | G82: Imelda | H82: Ipil | I82: Kabasalan | J82: Mabuhay | K82: Malangas | L82: Naga | M82: Olutanga | N82: Payao | O82: Roseller Lim | P82: Siay | Q82: Talusan | R82: Titay | S82: Tungawan
A83: Zamboanga del Norte | B83: AFHomesCities81 | C83: Bacungan | D83: Baliguian | E83: City of Dapitan | F83: City of Dipolog | G83: Godod | H83: Gutalac | I83: Jose Dalman | J83: Kalawit | K83: Katipunan | L83: La Libertad | M83: Labason | N83: Liloy | O83: Manukan | P83: Mutia | Q83: Piñan | R83: Polanco | S83: Pres. Manuel A. Roxas | T83: Rizal | U83: Salug | V83: Sergio Osmeña Sr. | W83: Siayan | X83: Sibuco | Y83: Sibutad | Z83: Sindangan | AA83: Siocon | AB83: Sirawai | AC83: Tampilisan
A84: Zamboanga del Sur | B84: AFHomesCities82 | C84: Aurora | D84: Bayog | E84: City of Pagadian | F84: City of Zamboanga | G84: Dimataling | H84: Dinas | I84: Dumalinao | J84: Dumingag | K84: Guipos | L84: Josefina | M84: Kumalarang | N84: Labangan | O84: Lakewood | P84: Lapuyan | Q84: Mahayag | R84: Margosatubig | S84: Midsalip | T84: Molave | U84: Pitogo | V84: Ramon Magsaysay | W84: San Miguel | X84: San Pablo | Y84: Sominot | Z84: Tabina | AA84: Tambulig | AB84: Tigbao | AC84: Tukuran | AD84: Vincenzo A. Sagun
A85: Abra|Bangued | B85: AFHomesBarangays0 | C85: Agtangao | D85: Angad | E85: Bangbangar | F85: Bañacao | G85: Cabuloan | H85: Calaba | I85: Cosili East | J85: Cosili West | K85: Dangdangla | L85: Lingtan | M85: Lipcan | N85: Lubong | O85: Macarcarmay | P85: Macray | Q85: Malita | R85: Maoay | S85: Palao | T85: Patucannay | U85: Sagap | V85: San Antonio | W85: Santa Rosa | X85: Sao-atan | Y85: Sappaac | Z85: Tablac | AA85: Zone 1 Pob. | AB85: Zone 2 Pob. | AC85: Zone 3 Pob. | AD85: Zone 4 Pob. | AE85: Zone 5 Pob. | AF85: Zone 6 Pob. | AG85: Zone 7 Pob.
A86: Abra|Boliney | B86: AFHomesBarangays1 | C86: Amti | D86: Bao-yan | E86: Danac East | F86: Danac West | G86: Dao-angan | H86: Dumagas | I86: Kilong-Olao | J86: Poblacion
A87: Abra|Bucay | B87: AFHomesBarangays2 | C87: Abang | D87: Bangbangcag | E87: Bangcagan | F87: Banglolao | G87: Bugbog | H87: Calao | I87: Dugong | J87: Labon | K87: Layugan | L87: Madalipay | M87: North Poblacion | N87: Pagala | O87: Pakiling | P87: Palaquio | Q87: Patoc | R87: Quimloong | S87: Salnec | T87: San Miguel | U87: Siblong | V87: South Poblacion | W87: Tabiog
A88: Abra|Bucloc | B88: AFHomesBarangays3 | C88: Ducligan | D88: Labaan | E88: Lamao | F88: Lingey
A89: Abra|Daguioman | B89: AFHomesBarangays4 | C89: Ableg | D89: Cabaruyan | E89: Pikek | F89: Tui
A90: Abra|Danglas | B90: AFHomesBarangays5 | C90: Abaquid | D90: Cabaruan | E90: Caupasan | F90: Danglas | G90: Nagaparan | H90: Padangitan | I90: Pangal
A91: Abra|Dolores | B91: AFHomesBarangays6 | C91: Bayaan | D91: Cabaroan | E91: Calumbaya | F91: Cardona | G91: Isit | H91: Kimmalaba | I91: Libtec | J91: Lub-lubba | K91: Mudiit | L91: Namit-ingan | M91: Pacac | N91: Poblacion | O91: Salucag | P91: Talogtog | Q91: Taping
A92: Abra|La Paz | B92: AFHomesBarangays7 | C92: Benben | D92: Bulbulala | E92: Buli | F92: Canan | G92: Liguis | H92: Malabbaga | I92: Mudeng | J92: Pidipid | K92: Poblacion | L92: San Gregorio | M92: Toon | N92: Udangan
A93: Abra|Lacub | B93: AFHomesBarangays8 | C93: Bacag | D93: Buneg | E93: Guinguinabang | F93: Lan-ag | G93: Pacoc | H93: Poblacion
A94: Abra|Lagangilang | B94: AFHomesBarangays9 | C94: Aguet | D94: Bacooc | E94: Balais | F94: Cayapa | G94: Dalaguisen | H94: Laang | I94: Lagben | J94: Laguiben | K94: Nagtipulan | L94: Nagtupacan | M94: Paganao | N94: Pawa | O94: Poblacion | P94: Presentar | Q94: San Isidro | R94: Tagodtod | S94: Taping
A95: Abra|Lagayan | B95: AFHomesBarangays10 | C95: Ba-i | D95: Collago | E95: Pang-ot | F95: Poblacion | G95: Pulot
A96: Abra|Langiden | B96: AFHomesBarangays11 | C96: Baac | D96: Dalayap | E96: Mabungtot | F96: Malapaao | G96: Poblacion | H96: Quillat
A97: Abra|Licuan-Baay | B97: AFHomesBarangays12 | C97: Bonglo | D97: Bulbulala | E97: Cawayan | F97: Domenglay | G97: Lenneng | H97: Mapisla | I97: Mogao | J97: Nalbuan | K97: Poblacion | L97: Subagan | M97: Tumalip
A98: Abra|Luba | B98: AFHomesBarangays13 | C98: Ampalioc | D98: Barit | E98: Gayaman | F98: Lul-luno | G98: Luzong | H98: Nagbukel-Tuquipa | I98: Poblacion | J98: Sabnangan
A99: Abra|Malibcong | B99: AFHomesBarangays14 | C99: Bayabas | D99: Binasaran | E99: Buanao | F99: Dulao | G99: Duldulao | H99: Gacab | I99: Lat-ey | J99: Malibcong | K99: Mataragan | L99: Pacgued | M99: Taripan | N99: Umnap
A100: Abra|Manabo | B100: AFHomesBarangays15 | C100: Ayyeng | D100: Catacdegan Nuevo | E100: Catacdegan Viejo | F100: Luzong | G100: San Jose Norte | H100: San Jose Sur | I100: San Juan Norte | J100: San Juan Sur | K100: San Ramon East | L100: San Ramon West | M100: Santo Tomas
...

Sheet Postal Codes
A1: Address | B1: Verified postal code
A2: Abra|Bangued | B2: 2800
A3: Abra|Boliney | B3: 2815
A4: Abra|Bucay | B4: 2805
A5: Abra|Bucloc | B5: 2817
A6: Abra|Daguioman | B6: 2816
A7: Abra|Danglas | B7: 2825
A8: Abra|Dolores | B8: 2801
A9: Abra|La Paz | B9: 2826
A10: Abra|Lacub | B10: 2821
A11: Abra|Lagayan | B11: 2824
A12: Abra|Langiden | B12: 2807
... A1516: Zamboanga del Sur|Tukuran | B1516: 7019
